libertai_agents/__init__.py
libertai_agents/agents/__init__.py
libertai_agents/agents/agent.py
libertai_agents/agents/self_funded/__init__.py
libertai_agents/agents/self_funded/abis/uniswap_router.json
libertai_agents/agents/self_funded/abis/uniswap_v3_pool.json
libertai_agents/agents/self_funded/agent.py
libertai_agents/agents/self_funded/constants.py
libertai_agents/agents/self_funded/interfaces.py
libertai_agents/agents/self_funded/provider.py
libertai_agents/interfaces/__init__.py
libertai_agents/interfaces/llamacpp.py
libertai_agents/interfaces/messages.py
libertai_agents/interfaces/models.py
libertai_agents/interfaces/tools.py
libertai_agents/models/__init__.py
libertai_agents/models/base.py
libertai_agents/models/hermes.py
libertai_agents/models/mistral.py
libertai_agents/models/models.py
libertai_agents/utils.py
libertai_agents-0.2.0.dist-info/METADATA
libertai_agents-0.2.0.dist-info/WHEEL
libertai_agents-0.2.0.dist-info/RECORD
